partis_schema-0.1.4.data/purelib/partis/schema_meta/struct.py
partis_schema-0.1.4.data/purelib/partis/schema_meta/property.py
partis_schema-0.1.4.data/purelib/partis/schema_meta/__init__.py
partis_schema-0.1.4.data/purelib/partis/schema_meta/base.py
partis_schema-0.1.4.data/purelib/partis/schema_meta/prim.py
partis_schema-0.1.4.data/purelib/partis/schema_meta/schema.py
partis_schema-0.1.4.data/purelib/partis/schema_meta/eval.py
partis_schema-0.1.4.data/purelib/partis/schema_meta/valued.py
partis_schema-0.1.4.data/purelib/partis/schema/__init__.py
partis_schema-0.1.4.data/purelib/partis/schema/color.py
partis_schema-0.1.4.data/purelib/partis/schema/prim/map_prim.py
partis_schema-0.1.4.data/purelib/partis/schema/prim/int_prim.py
partis_schema-0.1.4.data/purelib/partis/schema/prim/__init__.py
partis_schema-0.1.4.data/purelib/partis/schema/prim/path_prim.py
partis_schema-0.1.4.data/purelib/partis/schema/prim/any_prim.py
partis_schema-0.1.4.data/purelib/partis/schema/prim/base.py
partis_schema-0.1.4.data/purelib/partis/schema/prim/union_prim.py
partis_schema-0.1.4.data/purelib/partis/schema/prim/str_prim.py
partis_schema-0.1.4.data/purelib/partis/schema/prim/pass_prim.py
partis_schema-0.1.4.data/purelib/partis/schema/prim/seq_prim.py
partis_schema-0.1.4.data/purelib/partis/schema/prim/bool_prim.py
partis_schema-0.1.4.data/purelib/partis/schema/prim/float_prim.py
partis_schema-0.1.4.data/purelib/partis/schema/hint.py
partis_schema-0.1.4.data/purelib/partis/schema/valued/__init__.py
partis_schema-0.1.4.data/purelib/partis/schema/valued/bool_valued.py
partis_schema-0.1.4.data/purelib/partis/schema/valued/str_valued.py
partis_schema-0.1.4.data/purelib/partis/schema/valued/path_valued.py
partis_schema-0.1.4.data/purelib/partis/schema/valued/seq_valued.py
partis_schema-0.1.4.data/purelib/partis/schema/valued/struct_valued.py
partis_schema-0.1.4.data/purelib/partis/schema/valued/map_valued.py
partis_schema-0.1.4.dist-info/METADATA
partis_schema-0.1.4.dist-info/LICENSE.txt
partis_schema-0.1.4.dist-info/top_level.txt
partis_schema-0.1.4.dist-info/entry_points.txt
partis_schema-0.1.4.dist-info/WHEEL
partis_schema-0.1.4.dist-info/RECORD
