Metadata-Version: 2.1
Name: partis-schema
Version: 0.1.4
Requires-Python: >=3.6.2
Maintainer-email: "Nanohmics Inc." <software.support@nanohmics.com>
Summary: Base classes for defining JSON-compatible schemas
License-File: LICENSE.txt
Classifier: License :: OSI Approved :: BSD License
Classifier: Intended Audience :: Developers
Classifier: Topic :: Software Development :: Libraries
Classifier: Programming Language :: Python :: 3
Classifier: Operating System :: POSIX :: Linux
Classifier: Operating System :: Microsoft :: Windows
Classifier: Programming Language :: Python
Classifier: Development Status :: 4 - Beta
Provides-Extra: doc
Requires-Dist: cheetah3<4.0.0,>=3.2.4
Requires-Dist: ruamel.yaml>=0.16.5
Requires-Dist: overrides<4.0.0,>=3.1.0
Requires-Dist: pygments>=2.9.0
Requires-Dist: partis-pyproj>=0.1.4
Requires-Dist: partis-utils[lint]>=0.1.4
Requires-Dist: tomli>=1.2.3
Requires-Dist: partis-utils[sphinx]>=0.1.4; extra == "doc"
